FlexableThreadPoolExecutor/__init__.py
FlexableThreadPoolExecutor/flexable_thread.py
StopableThreadJob/__init__.py
StopableThreadJob/job_manager.py
stopable_thread_job-1.0.1.dist-info/LICENSE
stopable_thread_job-1.0.1.dist-info/METADATA
stopable_thread_job-1.0.1.dist-info/WHEEL
stopable_thread_job-1.0.1.dist-info/top_level.txt
stopable_thread_job-1.0.1.dist-info/RECORD
