Metadata-Version: 2.1
Name: stopable-thread-job
Version: 1.0.1
Summary: 可停止线程任务管理器
Home-page: https://github.com/AlitaIcon/StopableThreadJob
Author: alita
Author-email: 1906321518@qq.com
License: MIT
Project-URL: Documentation, https://github.com/AlitaIcon/StopableThreadJob
Classifier: Programming Language :: Python :: 3
Classifier: License :: OSI Approved :: MIT License
Classifier: Operating System :: OS Independent
Requires-Python: >=3.7
License-File: LICENSE
Requires-Dist: loguru (>=0.6.0)
